nic2proxy/README.MD
nic2proxy/__init__.py
nic2proxy/requirements.txt
nic2proxy/s5light-windows-amd64-v3.exe
nic2proxy/thirdparty.json
nic2proxy-0.10.dist-info/LICENSE.rst
nic2proxy-0.10.dist-info/METADATA
nic2proxy-0.10.dist-info/WHEEL
nic2proxy-0.10.dist-info/top_level.txt
nic2proxy-0.10.dist-info/RECORD
