Metadata-Version: 2.1
Name: nic2proxy
Version: 0.10
Summary: Creates Proxies and binds them to a NIC - Windows only
Home-page: https://github.com/hansalemaos/nic2proxy
Author: Johannes Fischer
Author-email: aulasparticularesdealemaosp@gmail.com
License: MIT
Keywords: Proxies,NIC
Classifier: Development Status :: 4 - Beta
Classifier: Programming Language :: Python :: 3 :: Only
Classifier: Programming Language :: Python :: 3.10
Classifier: Topic :: Software Development :: Libraries :: Python Modules
Classifier: Topic :: Utilities
License-File: LICENSE.rst
Requires-Dist: getpublicipv4
Requires-Dist: touchtouch
